alvadescpy/__init__.py
alvadescpy/functions.py
alvadescpy/wrapper.py
alvadescpy-0.1.4.dist-info/LICENSE
alvadescpy-0.1.4.dist-info/METADATA
alvadescpy-0.1.4.dist-info/WHEEL
alvadescpy-0.1.4.dist-info/top_level.txt
alvadescpy-0.1.4.dist-info/RECORD
