Metadata-Version: 2.1
Name: alvadescpy
Version: 0.1.4
Summary: Python wrapper for alvaDesc software
Author-email: Travis Kessler <travis.j.kessler@gmail.com>
Project-URL: Homepage, https://github.com/ecrl/alvadescpy
Project-URL: Bug Tracker, https://github.com/ecrl/alvadescpy/issues
Classifier: Programming Language :: Python :: 3.11
Classifier: License :: OSI Approved :: MIT License
Classifier: Operating System :: OS Independent
Requires-Python: >=3.11
License-File: LICENSE
